file_crusher/CompressionPostprocessor.py
file_crusher/__init__.py
file_crusher/__main__.py
file_crusher/advpng_compressor.py
file_crusher/batch_processor.py
file_crusher/config.py
file_crusher/cpdfsqueeze_compressor.py
file_crusher/file_operations.py
file_crusher/pdf_compressor.py
file_crusher/pipeline_processor.py
file_crusher/png_compressor.py
file_crusher/pngcrush_compressor.py
file_crusher/pngquant_compressor.py
file_crusher/processor.py
file_crusher/compressor_lib/advpng/LICENCE.txt
file_crusher/compressor_lib/advpng/advpng.exe
file_crusher/compressor_lib/cpdfsqueeze/LICENCE.txt
file_crusher/compressor_lib/cpdfsqueeze/cpdfsqueeze.exe
file_crusher/compressor_lib/pngcrush/LICENCE.txt
file_crusher/compressor_lib/pngcrush/pngcrush.exe
file_crusher/compressor_lib/pngquant/LICENCE.txt
file_crusher/compressor_lib/pngquant/pngquant.exe
file_crusher/converter/__init__.py
file_crusher/converter/image_to_pdf_converter.py
file_crusher/converter/pdf_merger.py
file_crusher/converter/pdf_to_image_converter.py
file_crusher-0.2.2.dist-info/METADATA
file_crusher-0.2.2.dist-info/WHEEL
file_crusher-0.2.2.dist-info/top_level.txt
file_crusher-0.2.2.dist-info/RECORD
